pydantic_nested/model.py
pydantic_nested-0.1.2.dist-info/METADATA
pydantic_nested-0.1.2.dist-info/WHEEL
pydantic_nested-0.1.2.dist-info/licenses/LICENSE
pydantic_nested-0.1.2.dist-info/RECORD
