Metadata-Version: 2.4
Name: pydantic-nested
Version: 0.1.2
Summary: Pydantic models from nested dictionaries
Author: Karolis Kluonaitis
License-File: LICENSE
Requires-Python: >=3.11
Requires-Dist: pydantic>=2.11.7
